Workbook

Sheet Assumptions
B1: BakiBondhu — Year 1 Financial Model
B2: Pick a scenario in the yellow cell — the whole model switches. Then fine-tune any blue input.
B4: LEGEND: yellow = choose / key · blue = input you can change · black = calculated
B5: ▶ ACTIVE SCENARIO | C5: Base | D5: ← change this one cell to switch Pessimistic / Base / Optimistic
B6: ACTIVE DRIVERS
B7: Subscription price — ARPU (৳/merchant/mo) | C7: =INDEX($C$17:$C$20,MATCH($C$5,$B$17:$B$20,0)) | D7: ↳ by scenario
B8: Monthly churn rate | C8: =INDEX($D$17:$D$20,MATCH($C$5,$B$17:$B$20,0)) | D8: ↳ by scenario
B9: Reminders per merchant / month | C9: 30 | D9: ↳ input
B10: Cost per SMS (৳) | C10: 0.35 | D10: ↳ input
B11: USD–BDT rate (memo, USD one-offs) | C11: 120 | D11: ↳ input
B13: Founder salary = ৳0 (sweat equity). Freelance income is personal runway on the P&L, not business revenue.
B15: SCENARIO LEVERS — edit any of these three rows
B16: Scenario | C16: ARPU | D16: Churn | E16: M1 | F16: M2 | G16: M3 | H16: M4 | I16: M5 | J16: M6 | K16: M7 | L16: M8 | M16: M9 | N16: M10 | O16: M11 | P16: M12
B17: Nobody pays | C17: 0 | D17: 0 | E17: 0 | F17: 0 | G17: 0 | H17: 0 | I17: 0 | J17: 0 | K17: 0 | L17: 0 | M17: 0 | N17: 0 | O17: 0 | P17: 0
B18: Pessimistic | C18: 150 | D18: 0.1 | E18: 0 | F18: 0 | G18: 0 | H18: 0 | I18: 0 | J18: 0 | K18: 10 | L18: 15 | M18: 25 | N18: 35 | O18: 50 | P18: 70
B19: Base | C19: 200 | D19: 0.05 | E19: 0 | F19: 0 | G19: 0 | H19: 0 | I19: 0 | J19: 0 | K19: 25 | L19: 40 | M19: 60 | N19: 90 | O19: 130 | P19: 180
B20: Optimistic | C20: 250 | D20: 0.03 | E20: 0 | F20: 0 | G20: 0 | H20: 0 | I20: 0 | J20: 0 | K20: 40 | L20: 70 | M20: 110 | N20: 160 | O20: 230 | P20: 320
B22: M1–M12 = new paying merchants added each month. Pre-revenue while you build (M1–M6), monetise from M7. 'Nobody pays' = the true floor: revenue stays ৳0 all year.

Sheet Monthly P&L
A1: Monthly P&L — Year 1 (৳)
A2: =" Active scenario: "&Assumptions!C5&" (blue rows are editable; new-merchant ramp is driven by the scenario)"
A3: Month | B3: 1 | C3: 2 | D3: 3 | E3: 4 | F3: 5 | G3: 6 | H3: 7 | I3: 8 | J3: 9 | K3: 10 | L3: 11 | M3: 12
A4: Phase | B4: Validate | C4: Validate | D4: Validate | E4: Build | F4: Build | G4: Build/Pilot | H4: Monetise | I4: Monetise | J4: Monetise | K4: Monetise | L4: Monetise | M4: Monetise
A5: PAYING MERCHANTS
A6: Paying merchants — beginning | B6: 0 | C6: =B9 | D6: =C9 | E6: =D9 | F6: =E9 | G6: =F9 | H6: =G9 | I6: =H9 | J6: =I9 | ... M6: =L9
A7: + New paying merchants (by scenario) | B7: =INDEX(Assumptions!E$17:E$20,MATCH(Assumptions!$C$5,Assumptions!$B$17:$B$20,0)) | C7: =INDEX(Assumptions!F$17:F$20,MATCH(Assumptions!$C$5,Assumptions!$B$17:$B$20,0)) | D7: =INDEX(Assumptions!G$17:G$20,MATCH(Assumptions!$C$5,Assumptions!$B$17:$B$20,0)) | E7: =INDEX(Assumptions!H$17:H$20,MATCH(Assumptions!$C$5,Assumptions!$B$17:$B$20,0)) | F7: =INDEX(Assumptions!I$17:I$20,MATCH(Assumptions!$C$5,Assumptions!$B$17:$B$20,0)) | G7: =INDEX(Assumptions!J$17:J$20,MATCH(Assumptions!$C$5,Assumptions!$B$17:$B$20,0)) | H7: =INDEX(Assumptions!K$17:K$20,MATCH(Assumptions!$C$5,Assumptions!$B$17:$B$20,0)) | I7: =INDEX(Assumptions!L$17:L$20,MATCH(Assumptions!$C$5,Assumptions!$B$17:$B$20,0)) | ... M7: =INDEX(Assumptions!P$17:P$20,MATCH(Assumptions!$C$5,Assumptions!$B$17:$B$20,0))
A8: − Churned | B8: =-ROUND(B6*Assumptions!$C$8,0) | C8: =-ROUND(C6*Assumptions!$C$8,0) | D8: =-ROUND(D6*Assumptions!$C$8,0) | E8: =-ROUND(E6*Assumptions!$C$8,0) | F8: =-ROUND(F6*Assumptions!$C$8,0) | G8: =-ROUND(G6*Assumptions!$C$8,0) | H8: =-ROUND(H6*Assumptions!$C$8,0) | I8: =-ROUND(I6*Assumptions!$C$8,0) | ... M8: =-ROUND(M6*Assumptions!$C$8,0)
A9: =Paying merchants — ending | B9: =B6+B7+B8 | C9: =C6+C7+C8 | D9: =D6+D7+D8 | E9: =E6+E7+E8 | F9: =F6+F7+F8 | G9: =G6+G7+G8 | H9: =H6+H7+H8 | I9: =I6+I7+I8 | ... M9: =M6+M7+M8
A10: Average paying (for revenue) | B10: =(B6+B9)/2 | C10: =(C6+C9)/2 | D10: =(D6+D9)/2 | E10: =(E6+E9)/2 | F10: =(F6+F9)/2 | G10: =(G6+G9)/2 | H10: =(H6+H9)/2 | I10: =(I6+I9)/2 | ... M10: =(M6+M9)/2
A11: REVENUE (৳ / month)
A12: Subscription revenue | B12: =ROUND(B10*Assumptions!$C$7,0) | C12: =ROUND(C10*Assumptions!$C$7,0) | D12: =ROUND(D10*Assumptions!$C$7,0) | E12: =ROUND(E10*Assumptions!$C$7,0) | F12: =ROUND(F10*Assumptions!$C$7,0) | G12: =ROUND(G10*Assumptions!$C$7,0) | H12: =ROUND(H10*Assumptions!$C$7,0) | I12: =ROUND(I10*Assumptions!$C$7,0) | ... M12: =ROUND(M10*Assumptions!$C$7,0)
A13: Total revenue | B13: =B12 | C13: =C12 | D13: =D12 | E13: =E12 | F13: =F12 | G13: =G12 | H13: =H12 | I13: =I12 | ... M13: =M12
A14: OPERATING COSTS (৳ / month)
A15: SMS / reminder cost | B15: =ROUND(B10*Assumptions!$C$9*Assumptions!$C$10,0) | C15: =ROUND(C10*Assumptions!$C$9*Assumptions!$C$10,0) | D15: =ROUND(D10*Assumptions!$C$9*Assumptions!$C$10,0) | E15: =ROUND(E10*Assumptions!$C$9*Assumptions!$C$10,0) | F15: =ROUND(F10*Assumptions!$C$9*Assumptions!$C$10,0) | G15: =ROUND(G10*Assumptions!$C$9*Assumptions!$C$10,0) | H15: =ROUND(H10*Assumptions!$C$9*Assumptions!$C$10,0) | I15: =ROUND(I10*Assumptions!$C$9*Assumptions!$C$10,0) | ... M15: =ROUND(M10*Assumptions!$C$9*Assumptions!$C$10,0)
A16: Hosting & infrastructure | B16: 0 | C16: 0 | D16: 0 | E16: 0 | F16: 0 | G16: 0 | H16: 0 | I16: 0 | J16: 0 | K16: 1500 | L16: 1500 | M16: 2000
A17: Tools & misc | B17: 500 | C17: 500 | D17: 500 | E17: 500 | F17: 500 | G17: 500 | H17: 500 | I17: 500 | J17: 500 | K17: 500 | L17: 500 | M17: 500
A18: One-time costs | B18: 1500 | C18: 0 | D18: 0 | E18: 0 | F18: 0 | G18: 3000 | H18: 0 | I18: 0 | J18: 0 | K18: 0 | L18: 0 | M18: 0
A19: Total costs | B19: =B15+B16+B17+B18 | C19: =C15+C16+C17+C18 | D19: =D15+D16+D17+D18 | E19: =E15+E16+E17+E18 | F19: =F15+F16+F17+F18 | G19: =G15+G16+G17+G18 | H19: =H15+H16+H17+H18 | I19: =I15+I16+I17+I18 | ... M19: =M15+M16+M17+M18
A20: RESULT (৳)
A21: Net profit / (loss) — business | B21: =B13-B19 | C21: =C13-C19 | D21: =D13-D19 | E21: =E13-E19 | F21: =F13-F19 | G21: =G13-G19 | H21: =H13-H19 | I21: =I13-I19 | ... M21: =M13-M19
A22: Cumulative net — business | B22: =B21 | C22: =B22+C21 | D22: =C22+D21 | E22: =D22+E21 | F22: =E22+F21 | G22: =F22+G21 | H22: =G22+H21 | I22: =H22+I21 | J22: =I22+J21 | ... M22: =L22+M21
A23: (helper) break-even month | B23: =IF(B21>=0,B3,"") | C23: =IF(C21>=0,C3,"") | D23: =IF(D21>=0,D3,"") | E23: =IF(E21>=0,E3,"") | F23: =IF(F21>=0,F3,"") | G23: =IF(G21>=0,G3,"") | H23: =IF(H21>=0,H3,"") | I23: =IF(I21>=0,I3,"") | ... M23: =IF(M21>=0,M3,"")
A24: FOUNDER RUNWAY — personal, memo only (NOT business revenue)
A25: Freelance income (personal) | B25: 40000 | C25: 40000 | D25: 40000 | E25: 40000 | F25: 40000 | G25: 40000 | H25: 40000 | I25: 40000 | J25: 40000 | K25: 30000 | L25: 30000 | M25: 20000
A26: Net incl. freelance | B26: =B21+B25 | C26: =C21+C25 | D26: =D21+D25 | E26: =E21+E25 | F26: =F21+F25 | G26: =G21+G25 | H26: =H21+H25 | I26: =I21+I25 | ... M26: =M21+M25
A27: Cumulative incl. freelance | B27: =B26 | C27: =B27+C26 | D27: =C27+D26 | E27: =D27+E26 | F27: =E27+F26 | G27: =F27+G26 | H27: =G27+H26 | I27: =H27+I26 | J27: =I27+J26 | ... M27: =L27+M26

Sheet Summary
B1: Year 1 — Headline Numbers
B2: ="Active scenario: "&Assumptions!C5&" — switch it on the Assumptions tab"
B4: ACTIVE SCENARIO — BUSINESS
B5: Year 1 total revenue | C5: =SUM('Monthly P&L'!B13:M13)
B6: Year 1 total costs | C6: =SUM('Monthly P&L'!B19:M19)
B7: Year 1 net profit / (loss) | C7: =SUM('Monthly P&L'!B21:M21)
B8: Paying merchants at Month 12 | C8: ='Monthly P&L'!M9
B9: MRR at Month 12 | C9: ='Monthly P&L'!M13
B10: Monthly break-even | C10: =IF(COUNT('Monthly P&L'!B23:M23)=0,"After Yr 1","Month "&MIN('Monthly P&L'!B23:M23))
B11: Peak cash gap to cover (business) | C11: =-MIN('Monthly P&L'!B22:M22)
B13: FOUNDER RUNWAY (personal)
B14: Freelance income needed (Year 1) | C14: =SUM('Monthly P&L'!B25:M25)
B15: Combined cash at Month 12 | C15: ='Monthly P&L'!M27
B18: SCENARIO COMPARISON — snapshot at default inputs (toggle Active Scenario for the live model)
B19: Metric | C19: Nobody pays | D19: Pessimistic | E19: Base | F19: Optimistic
B20: Year 1 revenue | C20: 0 | D20: 54825 | E20: 196900 | F20: 442375
B21: Year 1 net | C21: -15500 | D21: 35488 | E21: 171063 | F21: 408296
B22: Paying merchants @ M12 | C22: 0 | D22: 177 | E22: 489 | F22: 891
B23: MRR @ M12 | C23: 0 | D23: 22200 | E23: 81400 | F23: 185000
B24: Break-even | C24: After Yr1 | D24: Month 7 | E24: Month 7 | F24: Month 7
B25: Peak cash gap | C25: 15500 | D25: 7500 | E25: 7500 | F25: 7500
